ScreenshotFormat/__init__.py
ScreenshotFormat-1.dist-info/LICENSE
ScreenshotFormat-1.dist-info/METADATA
ScreenshotFormat-1.dist-info/WHEEL
ScreenshotFormat-1.dist-info/top_level.txt
ScreenshotFormat-1.dist-info/RECORD
